freepbx_bulk_handler/Extension.py
freepbx_bulk_handler/__init__.py
freepbx_bulk_handler-0.61.dist-info/LICENSE.md
freepbx_bulk_handler-0.61.dist-info/METADATA
freepbx_bulk_handler-0.61.dist-info/WHEEL
freepbx_bulk_handler-0.61.dist-info/top_level.txt
freepbx_bulk_handler-0.61.dist-info/RECORD
